terraformvspherevm/__init__.py
terraformvspherevm/terraformvm.py
terraformvspherevm/terrascriptvspherevm.py
terraformvspherevm-0.0.13.dist-info/LICENSE.txt
terraformvspherevm-0.0.13.dist-info/METADATA
terraformvspherevm-0.0.13.dist-info/WHEEL
terraformvspherevm-0.0.13.dist-info/entry_points.txt
terraformvspherevm-0.0.13.dist-info/top_level.txt
terraformvspherevm-0.0.13.dist-info/RECORD
