Metadata-Version: 2.1
Name: terraformvspherevm
Version: 0.0.13
Summary: Create VSphere resources using terraform
Home-page: https://github.com/tsenay/python-terraformvpsherevm
Author: Thomas Senay
Author-email: tsenay.consulting@icloud.com
License: UNKNOWN
Project-URL: Bug Reports, https://github.com/tsenay/python-terraformvpsherevm/issues
Project-URL: Source, https://github.com/tsenay/python-terraformvpsherevm
Keywords: vpshere terraform
Platform: UNKNOWN
Classifier: Development Status :: 3 - Alpha
Classifier: Intended Audience :: Developers
Classifier: Topic :: Software Development :: Libraries
Classifier: License :: OSI Approved :: MIT License
Classifier: Programming Language :: Python :: 3.5
Classifier: Programming Language :: Python :: 3.6
Classifier: Programming Language :: Python :: 3.7
Requires-Python: >=3.6
Requires-Dist: terrascript
Requires-Dist: python-terraform
